[{"name":"China","alpha2Code":"CN","capital":"Jiangti","population":214451450,"area":578023},
{"name":"Indonesia","alpha2Code":"ID","capital":"Satowebrang","population":94872668,"area":984024},
{"name":"Belarus","alpha2Code":"BY","capital":"Borovlyany","population":119767373,"area":227185},
{"name":"Portugal","alpha2Code":"PT","capital":"Boavista","population":16913841,"area":181820},
{"name":"China","alpha2Code":"CN","capital":"Marelesu","population":95678337,"area":400177},
{"name":"Indonesia","alpha2Code":"ID","capital":"Pasirmukti","population":125267782,"area":657443},
{"name":"Malaysia","alpha2Code":"MY","capital":"Rawang","population":10449561,"area":888852},
{"name":"Ireland","alpha2Code":"IE","capital":"Prosperous","population":120321510,"area":520395},
{"name":"Palestinian Territory","alpha2Code":"PS","capital":"Ţūbās","population":51094812,"area":380264},
{"name":"Belgium","alpha2Code":"BE","capital":"Tournai","population":103674558,"area":290279},
{"name":"Thailand","alpha2Code":"TH","capital":"Wiang Nuea","population":158099415,"area":434030},
{"name":"Comoros","alpha2Code":"KM","capital":"Mtsamdou","population":250141780,"area":751741},
{"name":"Brazil","alpha2Code":"BR","capital":"Condado","population":80760933,"area":475893},
{"name":"Albania","alpha2Code":"AL","capital":"Golem","population":286621982,"area":879121},
{"name":"Brazil","alpha2Code":"BR","capital":"Ubatuba","population":160845674,"area":500862},
{"name":"Venezuela","alpha2Code":"VE","capital":"Pueblo Nuevo","population":100008274,"area":302153},
{"name":"Canada","alpha2Code":"CA","capital":"Château-Richer","population":24256543,"area":278725},
{"name":"Norway","alpha2Code":"NO","capital":"Steinkjer","population":299266888,"area":738656},
{"name":"China","alpha2Code":"CN","capital":"Lantang","population":79180077,"area":538945},
{"name":"Indonesia","alpha2Code":"ID","capital":"Paritjunus","population":191933159,"area":156884},
{"name":"Brazil","alpha2Code":"BR","capital":"Chã Grande","population":189013864,"area":746032},
{"name":"American Samoa","alpha2Code":"AS","capital":"Ta`ū","population":255743864,"area":175289},
{"name":"Indonesia","alpha2Code":"ID","capital":"Plandi","population":84946646,"area":156031},
{"name":"China","alpha2Code":"CN","capital":"Linshi","population":287076003,"area":422478},
{"name":"China","alpha2Code":"CN","capital":"Magaozhuang","population":102552299,"area":265384},
{"name":"Indonesia","alpha2Code":"ID","capital":"Karangsuko","population":206577664,"area":779253},
{"name":"Nepal","alpha2Code":"NP","capital":"Bāglung","population":143106215,"area":157016},
{"name":"United States","alpha2Code":"US","capital":"Springfield","population":1625530,"area":323216},
{"name":"Indonesia","alpha2Code":"ID","capital":"Matur","population":272713252,"area":124263},
{"name":"South Korea","alpha2Code":"KR","capital":"Daegu","population":198715476,"area":396721},
{"name":"Indonesia","alpha2Code":"ID","capital":"Sidayu","population":151739035,"area":519194},
{"name":"Poland","alpha2Code":"PL","capital":"Strzelin","population":137479118,"area":925837},
{"name":"Pakistan","alpha2Code":"PK","capital":"Jalālpur Pīrwāla","population":98435514,"area":477578},
{"name":"Indonesia","alpha2Code":"ID","capital":"Karangpawitan","population":118885705,"area":988346},
{"name":"Czech Republic","alpha2Code":"CZ","capital":"Fulnek","population":215507860,"area":630751},
{"name":"Philippines","alpha2Code":"PH","capital":"Veruela","population":202914036,"area":87067},
{"name":"Poland","alpha2Code":"PL","capital":"Garbów","population":205870203,"area":355772},
{"name":"United States","alpha2Code":"US","capital":"El Paso","population":279654834,"area":153729},
{"name":"Greece","alpha2Code":"GR","capital":"Grevená","population":191363508,"area":981249},
{"name":"Russia","alpha2Code":"RU","capital":"Ryazan’","population":119595405,"area":904324},
{"name":"France","alpha2Code":"FR","capital":"Nice","population":298048175,"area":894378},
{"name":"Gambia","alpha2Code":"GM","capital":"Abuko","population":56106449,"area":911954},
{"name":"China","alpha2Code":"CN","capital":"Jialu","population":224204237,"area":843931},
{"name":"Brazil","alpha2Code":"BR","capital":"João Câmara","population":245281385,"area":235359},
{"name":"South Korea","alpha2Code":"KR","capital":"Waegwan","population":14838087,"area":271734},
{"name":"Albania","alpha2Code":"AL","capital":"Trebisht-Muçinë","population":107212941,"area":240611},
{"name":"China","alpha2Code":"CN","capital":"Chang’an","population":43518994,"area":674298},
{"name":"Greece","alpha2Code":"GR","capital":"Mýki","population":7134202,"area":523054},
{"name":"Thailand","alpha2Code":"TH","capital":"Sirindhorn","population":41900594,"area":471731},
{"name":"China","alpha2Code":"CN","capital":"Longyuanba","population":191779909,"area":681946},
{"name":"China","alpha2Code":"CN","capital":"Lieqiao","population":239885419,"area":261688},
{"name":"Philippines","alpha2Code":"PH","capital":"Mabuhay","population":204517677,"area":698610},
{"name":"China","alpha2Code":"CN","capital":"Longchiqiao","population":46982459,"area":893001},
{"name":"Tunisia","alpha2Code":"TN","capital":"Jammāl","population":26611322,"area":79517},
{"name":"Serbia","alpha2Code":"RS","capital":"Belgrade","population":109705311,"area":543930},
{"name":"China","alpha2Code":"CN","capital":"Donggu","population":20272817,"area":279402},
{"name":"China","alpha2Code":"CN","capital":"Longmiao","population":67386425,"area":274800},
{"name":"China","alpha2Code":"CN","capital":"Beibao","population":274076468,"area":700095},
{"name":"Philippines","alpha2Code":"PH","capital":"Napuro","population":198237881,"area":81847},
{"name":"Czech Republic","alpha2Code":"CZ","capital":"Rybí","population":270975546,"area":25861},
{"name":"Saudi Arabia","alpha2Code":"SA","capital":"Al Muţayrifī","population":59445258,"area":948017},
{"name":"Russia","alpha2Code":"RU","capital":"Sovetskaya","population":78164184,"area":241279},
{"name":"France","alpha2Code":"FR","capital":"Orléans","population":188289646,"area":392623},
{"name":"China","alpha2Code":"CN","capital":"Xinyu","population":285177054,"area":726774},
{"name":"Bosnia and Herzegovina","alpha2Code":"BA","capital":"Mejdan - Obilićevo","population":105975332,"area":314332},
{"name":"Benin","alpha2Code":"BJ","capital":"Banikoara","population":281174359,"area":232183},
{"name":"Russia","alpha2Code":"RU","capital":"Kostino","population":49414773,"area":286930},
{"name":"Portugal","alpha2Code":"PT","capital":"Gafanha da Encarnação","population":173810892,"area":449283},
{"name":"Afghanistan","alpha2Code":"AF","capital":"Āsmār","population":143770254,"area":769740},
{"name":"Indonesia","alpha2Code":"ID","capital":"Lanta Timur","population":75781194,"area":508696},
{"name":"Ukraine","alpha2Code":"UA","capital":"Bilhorod-Dnistrovs’kyy","population":86215523,"area":584292},
{"name":"China","alpha2Code":"CN","capital":"Huashixia","population":299514399,"area":301402},
{"name":"China","alpha2Code":"CN","capital":"Nankengzi","population":58081856,"area":304527},
{"name":"Indonesia","alpha2Code":"ID","capital":"Banjar Sandinggianyar","population":96837636,"area":835062},
{"name":"Poland","alpha2Code":"PL","capital":"Wohyń","population":118103168,"area":130448},
{"name":"Czech Republic","alpha2Code":"CZ","capital":"Pardubice","population":191525298,"area":256297},
{"name":"Gabon","alpha2Code":"GA","capital":"Cocobeach","population":29909814,"area":513354},
{"name":"Indonesia","alpha2Code":"ID","capital":"Lewokluok","population":166949962,"area":887212},
{"name":"Brazil","alpha2Code":"BR","capital":"Salto de Pirapora","population":282078901,"area":320861},
{"name":"Philippines","alpha2Code":"PH","capital":"Silago","population":262802076,"area":95579},
{"name":"Portugal","alpha2Code":"PT","capital":"Água Retorta","population":46975427,"area":244351},
{"name":"Nigeria","alpha2Code":"NG","capital":"Kumagunnam","population":245903491,"area":833371},
{"name":"Thailand","alpha2Code":"TH","capital":"Khok Sung","population":244469171,"area":312035},
{"name":"France","alpha2Code":"FR","capital":"Fos-sur-Mer","population":126636565,"area":100966},
{"name":"China","alpha2Code":"CN","capital":"Yanglin","population":290670211,"area":109199},
{"name":"China","alpha2Code":"CN","capital":"Shinaihai","population":206233936,"area":483459},
{"name":"Indonesia","alpha2Code":"ID","capital":"Kampungmasjid","population":221269454,"area":982853},
{"name":"Portugal","alpha2Code":"PT","capital":"Sarilhos Grandes","population":11135700,"area":628752},
{"name":"Colombia","alpha2Code":"CO","capital":"Orocué","population":52827589,"area":106083},
{"name":"Tunisia","alpha2Code":"TN","capital":"Sidi Bouzid","population":252562227,"area":295791},
{"name":"France","alpha2Code":"FR","capital":"Saint-Malo","population":237376774,"area":490149},
{"name":"China","alpha2Code":"CN","capital":"Jiapeng","population":272231386,"area":110063},
{"name":"Botswana","alpha2Code":"BW","capital":"Ramotswa","population":281499716,"area":10666},
{"name":"Poland","alpha2Code":"PL","capital":"Wólka Pełkińska","population":196578187,"area":70835},
{"name":"Serbia","alpha2Code":"RS","capital":"Badovinci","population":151680530,"area":43849},
{"name":"Philippines","alpha2Code":"PH","capital":"San Mateo","population":152310561,"area":862430},
{"name":"Czech Republic","alpha2Code":"CZ","capital":"Milevsko","population":247823518,"area":386890},
{"name":"Greece","alpha2Code":"GR","capital":"Dióni","population":197640848,"area":541135},
{"name":"Japan","alpha2Code":"JP","capital":"Tahara","population":55610882,"area":138754},
{"name":"Indonesia","alpha2Code":"ID","capital":"Mbongawani","population":179374103,"area":529940}]